[
    {
        "input": "###S###\n#     #\n## ## #\n## ## #\n##E####",
        "expected_output": "###.###\n# ..  #\n##.## #\n##.## #\n##.####"
    },
    {
        "input": "##########\nS      ###\n### ## ###\n### #### E\n#        #\n##########",
        "expected_output": "##########\n....   ###\n###.## ###\n###.####..\n#  ......#\n##########"
    },
    {
        "input": "#####################\n### ## ##   #########\n##        #  ########\n## #########        #\n#   #S###    #### # #\n##E## ### ## #### # #\n##### ### ## ####   #\n#         #### ### ##\n## ######      ######\n#####################",
        "expected_output": "#####################\n### ## ##...#########\n##........#..########\n##.#########.       #\n# . #.###....#### # #\n##.##.###.## #### # #\n#####.###.## ####   #\n#    .....#### ### ##\n## ######      ######\n#####################"
    }
]

